gitorade.py
gitorade-1.0.8.dist-info/LICENSE
gitorade-1.0.8.dist-info/METADATA
gitorade-1.0.8.dist-info/WHEEL
gitorade-1.0.8.dist-info/entry_points.txt
gitorade-1.0.8.dist-info/top_level.txt
gitorade-1.0.8.dist-info/RECORD
